Workbook
Name Slicer_Region: #N/A
Name Slicer_Years__Invoice_Date: #N/A

Sheet Pivot table 1
A3: Sum of Total Sales | B3: Sum of Units Sold | C3: Average of Price per Unit | D3: Sum of Operating Profit
A4: 12016665 | B4: 24788610 | C4: 0.45216625 | D4: 4722496.8
A6: Sum of Total Sales | B6: Column Labels
B7: 2022 | C7: 2023 | D7: Grand Total
A9: Row Labels
A10: Coca-Cola | B10: 499102 | C10: 2268974.9 | D10: 2768076.9
A11: Dasani Water | B11: 469270.7 | C11: 1917827.8 | D11: 2387098.5
A12: Diet Coke | B12: 423758.7 | C12: 1633959.3 | D12: 2057718
A13: Fanta | B13: 315489.2 | C13: 1116062.9 | D13: 1431552.1
A14: Powerade | B14: 349533.9 | C14: 1302529.3 | D14: 1652063.2
A15: Sprite | B15: 366578 | C15: 1353578.3 | D15: 1720156.3
A16: Grand Total | B16: 2423732.5 | C16: 9592932.5 | D16: 12016665
A19: Years (Invoice Date) | B19: Quarters (Invoice Date) | C19: Sum of Total Sales | D19: Average of Operating Margin
A20: 2022 | B20: Qtr1 | C20: 692776.1 | D20: 0.40174684 | E20: =A20 -> 2022 | F20: =B20 -> Qtr1 | G20: =C20 -> 692776.1 | H20: =D20 -> 0.40174684
B21: Qtr2 | C21: 644203.9 | D21: 0.4 | F21: =B21 -> Qtr2 | G21: =C21 -> 644203.9 | H21: =D21 -> 0.4
B22: Qtr3 | C22: 719170.4 | D22: 0.41026549 | F22: =B22 -> Qtr3 | G22: =C22 -> 719170.4 | H22: =D22 -> 0.41026549
B23: Qtr4 | C23: 367582.1 | D23: 0.40243816 | F23: =B23 -> Qtr4 | G23: =C23 -> 367582.1 | H23: =D23 -> 0.40243816
A24: 2023 | B24: Qtr1 | C24: 1877584.3 | D24: 0.41657045 | E24: =A24 -> 2023 | F24: =B24 -> Qtr1 | G24: =C24 -> 1877584.3 | H24: =D24 -> 0.41657045
B25: Qtr2 | C25: 2379424.8 | D25: 0.42755819 | F25: =B25 -> Qtr2 | G25: =C25 -> 2379424.8 | H25: =D25 -> 0.42755819
B26: Qtr3 | C26: 2805752.5 | D26: 0.4347017 | F26: =B26 -> Qtr3 | G26: =C26 -> 2805752.5 | H26: =D26 -> 0.4347017
B27: Qtr4 | C27: 2530170.9 | D27: 0.42483933 | F27: =B27 -> Qtr4 | G27: =C27 -> 2530170.9 | H27: =D27 -> 0.42483933
A28: Grand Total | C28: 12016665 | D28: 0.42299129

Sheet Pivot table 2
A3: Sum of Total Sales | B3: Column Labels
A4: Row Labels | B4: 2022 | C4: 2023 | D4: Grand Total
A5: Amazon | B5: 276210 | C5: 1009698.7 | D5: 1285908.7
A6: BevCo | B6: 466788 | C6: 2327606.5 | D6: 2794394.5
A7: FizzyCo | B7: 161210.1 | C7: 2262827.1 | D7: 2424037.2
A8: Target | B8: 9250.3 | C8: 1341995 | D8: 1351245.3
A9: Walmart | B9: 339912.5 | C9: 580211 | D9: 920123.5
A10: West Soda | B10: 1170361.6 | C10: 2070594.2 | D10: 3240955.8
A11: Grand Total | B11: 2423732.5 | C11: 9592932.5 | D11: 12016665

Sheet Data
B2: Retailer Dataset
B4: Retailer | C4: Retailer ID | D4: Invoice Date | E4: Region | F4: State | G4: City | H4: Beverage Brand | I4: Price per Unit | J4: Units Sold | K4: Total Sales | L4: Operating Profit | M4: Operating Margin
B5: BevCo | C5: 1185732 | D5: 44562 | E5: Northeast | F5: New York | G5: New York | H5: Coca-Cola | I5: 0.5 | J5: 12000 | K5: 6000 | L5: 3000 | M5: 0.5
B6: BevCo | C6: 1185732 | D6: 44563 | E6: Northeast | F6: New York | G6: New York | H6: Diet Coke | I6: 0.5 | J6: 10000 | K6: 5000 | L6: 1500 | M6: 0.3
B7: BevCo | C7: 1185732 | D7: 44564 | E7: Northeast | F7: New York | G7: New York | H7: Sprite | I7: 0.4 | J7: 10000 | K7: 4000 | L7: 1400 | M7: 0.35
B8: BevCo | C8: 1185732 | D8: 44565 | E8: Northeast | F8: New York | G8: New York | H8: Fanta | I8: 0.45 | J8: 8500 | K8: 3825 | L8: 1338.75 | M8: 0.35
B9: BevCo | C9: 1185732 | D9: 44566 | E9: Northeast | F9: New York | G9: New York | H9: Powerade | I9: 0.6 | J9: 9000 | K9: 5400 | L9: 1620 | M9: 0.3
B10: BevCo | C10: 1185732 | D10: 44567 | E10: Northeast | F10: New York | G10: New York | H10: Dasani Water | I10: 0.5 | J10: 10000 | K10: 5000 | L10: 1250 | M10: 0.25
B11: BevCo | C11: 1185732 | D11: 44568 | E11: Northeast | F11: New York | G11: New York | H11: Coca-Cola | I11: 0.5 | J11: 12500 | K11: 6250 | L11: 3125 | M11: 0.5
B12: BevCo | C12: 1185732 | D12: 44569 | E12: Northeast | F12: New York | G12: New York | H12: Diet Coke | I12: 0.5 | J12: 9000 | K12: 4500 | L12: 1350 | M12: 0.3
B13: BevCo | C13: 1185732 | D13: 44582 | E13: Northeast | F13: New York | G13: New York | H13: Sprite | I13: 0.4 | J13: 9500 | K13: 3800 | L13: 1330 | M13: 0.35
B14: BevCo | C14: 1185732 | D14: 44583 | E14: Northeast | F14: New York | G14: New York | H14: Fanta | I14: 0.45 | J14: 8250 | K14: 3712.5 | L14: 1299.375 | M14: 0.35
B15: BevCo | C15: 1185732 | D15: 44584 | E15: Northeast | F15: New York | G15: New York | H15: Powerade | I15: 0.6 | J15: 9000 | K15: 5400 | L15: 1620 | M15: 0.3
B16: BevCo | C16: 1185732 | D16: 44585 | E16: Northeast | F16: New York | G16: New York | H16: Dasani Water | I16: 0.5 | J16: 10000 | K16: 5000 | L16: 1250 | M16: 0.25
... B9652: BevCo | C9652: 1185732 | D9652: 44979 | E9652: Northeast | F9652: New Hampshire | G9652: Manchester | H9652: Sprite | I9652: 0.29 | J9652: 830 | K9652: 240.7 | L9652: 64.989 | M9652: 0.27

Sheet Dashboard
C11: sales by bevarage brand | H11: sales by retailer
C12: Brand | D12: Sales 2022 | E12: Sales 2023 | F12: Variance | H12: Brand | I12: Sales 2022 | J12: Sales 2023 | K12: Variance
C13: ='Pivot table 1'!A10 -> Coca-Cola | D13: ='Pivot table 1'!B10 -> 499102 | E13: ='Pivot table 1'!C10 -> 2268974.9 | F13: =E13-D13 -> 1769872.9 | H13: ='Pivot table 2'!A5 -> Amazon | I13: ='Pivot table 2'!B5 -> 276210 | J13: ='Pivot table 2'!C5 -> 1009698.7 | K13: =J13-I13 -> 733488.7
C14: ='Pivot table 1'!A11 -> Dasani Water | D14: ='Pivot table 1'!B11 -> 469270.7 | E14: ='Pivot table 1'!C11 -> 1917827.8 | F14: =E14-D14 -> 1448557.1 | H14: ='Pivot table 2'!A6 -> BevCo | I14: ='Pivot table 2'!B6 -> 466788 | J14: ='Pivot table 2'!C6 -> 2327606.5 | K14: =J14-I14 -> 1860818.5
C15: ='Pivot table 1'!A12 -> Diet Coke | D15: ='Pivot table 1'!B12 -> 423758.7 | E15: ='Pivot table 1'!C12 -> 1633959.3 | F15: =E15-D15 -> 1210200.6 | H15: ='Pivot table 2'!A7 -> FizzyCo | I15: ='Pivot table 2'!B7 -> 161210.1 | J15: ='Pivot table 2'!C7 -> 2262827.1 | K15: =J15-I15 -> 2101617
C16: ='Pivot table 1'!A13 -> Fanta | D16: ='Pivot table 1'!B13 -> 315489.2 | E16: ='Pivot table 1'!C13 -> 1116062.9 | F16: =E16-D16 -> 800573.7 | H16: ='Pivot table 2'!A8 -> Target | I16: ='Pivot table 2'!B8 -> 9250.3 | J16: ='Pivot table 2'!C8 -> 1341995 | K16: =J16-I16 -> 1332744.7
C17: ='Pivot table 1'!A14 -> Powerade | D17: ='Pivot table 1'!B14 -> 349533.9 | E17: ='Pivot table 1'!C14 -> 1302529.3 | F17: =E17-D17 -> 952995.4 | H17: ='Pivot table 2'!A9 -> Walmart | I17: ='Pivot table 2'!B9 -> 339912.5 | J17: ='Pivot table 2'!C9 -> 580211 | K17: =J17-I17 -> 240298.5
C18: ='Pivot table 1'!A15 -> Sprite | D18: ='Pivot table 1'!B15 -> 366578 | E18: ='Pivot table 1'!C15 -> 1353578.3 | F18: =E18-D18 -> 987000.3 | H18: ='Pivot table 2'!A10 -> West Soda | I18: ='Pivot table 2'!B10 -> 1170361.6 | J18: ='Pivot table 2'!C10 -> 2070594.2 | K18: =J18-I18 -> 900232.6
C19: ='Pivot table 1'!A16 -> Grand Total | D19: ='Pivot table 1'!B16 -> 2423732.5 | E19: ='Pivot table 1'!C16 -> 9592932.5 | F19: =E19-D19 -> 7169200 | H19: ='Pivot table 2'!A11 -> Grand Total | I19: ='Pivot table 2'!B11 -> 2423732.5 | J19: ='Pivot table 2'!C11 -> 9592932.5 | K19: =J19-I19 -> 7169200
C23: sales and opertating profit margin by quarter
